starlite/__init__.py
starlite/__main__.py
starlite/app.py
starlite/asgi/__init__.py
starlite/asgi/asgi_router.py
starlite/asgi/routing_trie/__init__.py
starlite/asgi/routing_trie/mapping.py
starlite/asgi/routing_trie/traversal.py
starlite/asgi/routing_trie/types.py
starlite/asgi/routing_trie/validate.py
starlite/asgi/utils.py
starlite/cache/__init__.py
starlite/cache/base.py
starlite/cache/memcached_cache_backend.py
starlite/cache/redis_cache_backend.py
starlite/cache/simple_cache_backend.py
starlite/cli/__init__.py
starlite/cli/commands/__init__.py
starlite/cli/commands/core.py
starlite/cli/commands/schema.py
starlite/cli/commands/sessions.py
starlite/cli/main.py
starlite/cli/utils.py
starlite/config/__init__.py
starlite/config/allowed_hosts.py
starlite/config/app.py
starlite/config/cache.py
starlite/config/compression.py
starlite/config/cors.py
starlite/config/csrf.py
starlite/config/logging.py
starlite/config/openapi.py
starlite/config/static_files.py
starlite/config/template.py
starlite/connection/__init__.py
starlite/connection/base.py
starlite/connection/request.py
starlite/connection/websocket.py
starlite/constants.py
starlite/contrib/__init__.py
starlite/contrib/jinja.py
starlite/contrib/jwt/__init__.py
starlite/contrib/jwt/jwt_auth.py
starlite/contrib/jwt/jwt_token.py
starlite/contrib/jwt/middleware.py
starlite/contrib/mako.py
starlite/contrib/opentelemetry/__init__.py
starlite/contrib/opentelemetry/config.py
starlite/contrib/opentelemetry/middleware.py
starlite/contrib/opentelemetry/utils.py
starlite/controller.py
starlite/datastructures/__init__.py
starlite/datastructures/background_tasks.py
starlite/datastructures/cookie.py
starlite/datastructures/headers.py
starlite/datastructures/multi_dicts.py
starlite/datastructures/pagination.py
starlite/datastructures/provide.py
starlite/datastructures/response_containers.py
starlite/datastructures/response_header.py
starlite/datastructures/state.py
starlite/datastructures/upload_file.py
starlite-1.51.16.dist-info/LICENSE
starlite-1.51.16.dist-info/METADATA
starlite-1.51.16.dist-info/WHEEL
starlite-1.51.16.dist-info/entry_points.txt
starlite-1.51.16.dist-info/RECORD
