Metadata-Version: 2.1
Name: starlite
Version: 1.51.16
Summary: Performant, light and flexible ASGI API Framework
Home-page: https://litestar.dev
License: MIT
Keywords: http,asgi,starlite,framework,websocket
Author: Janek Nouvertné
Author-email: provinzkraut@posteo.de
Maintainer: Litestar Developers
Maintainer-email: hello@litestar.dev
Requires-Python: >=3.8,<4.0
Classifier: Development Status :: 5 - Production/Stable
Classifier: Environment :: Web Environment
Classifier: License :: OSI Approved :: MIT License
Classifier: Natural Language :: English
Classifier: Operating System :: OS Independent
Classifier: Programming Language :: Python
Classifier: Programming Language :: Python :: 3
Classifier: Programming Language :: Python :: 3.8
Classifier: Programming Language :: Python :: 3.9
Classifier: Programming Language :: Python :: 3.10
Classifier: Programming Language :: Python :: 3.11
Classifier: Programming Language :: Python :: 3.12
Classifier: Topic :: Internet :: WWW/HTTP
Classifier: Topic :: Software Development
Classifier: Topic :: Software Development :: Libraries
Classifier: Typing :: Typed
Provides-Extra: brotli
Provides-Extra: cli
Provides-Extra: cryptography
Provides-Extra: full
Provides-Extra: jinja
Provides-Extra: jwt
Provides-Extra: memcached
Provides-Extra: opentelemetry
Provides-Extra: picologging
Provides-Extra: redis
Provides-Extra: standard
Provides-Extra: structlog
Provides-Extra: tortoise-orm
Requires-Dist: aiomcache ; extra == "memcached" or extra == "full"
Requires-Dist: anyio (>=3,<4)
Requires-Dist: brotli ; extra == "brotli" or extra == "full"
Requires-Dist: click ; extra == "cli" or extra == "standard" or extra == "full"
Requires-Dist: cryptography ; extra == "cryptography" or extra == "jwt" or extra == "full"
Requires-Dist: fast-query-parsers
Requires-Dist: httpx (>=0.22)
Requires-Dist: importlib-metadata ; python_version < "3.10"
Requires-Dist: jinja2 (>=3.1.2) ; extra == "jinja" or extra == "standard" or extra == "full"
Requires-Dist: jsbeautifier ; extra == "cli" or extra == "standard"
Requires-Dist: mako (>=1.2.4)
Requires-Dist: msgspec (>=0.11.0)
Requires-Dist: multidict (>=6.0.2)
Requires-Dist: opentelemetry-instrumentation-asgi ; extra == "opentelemetry" or extra == "full"
Requires-Dist: picologging ; extra == "picologging" or extra == "standard" or extra == "full"
Requires-Dist: pydantic (<2)
Requires-Dist: pydantic-factories
Requires-Dist: pydantic-openapi-schema (>=1.5.0)
Requires-Dist: python-jose ; extra == "jwt" or extra == "full"
Requires-Dist: pyyaml
Requires-Dist: redis[hiredis] ; extra == "redis" or extra == "full"
Requires-Dist: rich (>=13.0.0) ; extra == "cli" or extra == "standard" or extra == "full"
Requires-Dist: structlog ; extra == "structlog" or extra == "full"
Requires-Dist: typing-extensions
Project-URL: Blog, https://blog.litestar.dev
Project-URL: Changelog, https://github.com/litestar-org/litestar/releases/
Project-URL: Documentation, https://docs.litestar.dev/1/
Project-URL: Discord, https://discord.gg/MmcwxztmQb
Project-URL: Issue Tracker, https://github.com/litestar-org/litestar/issues?q=is%3Aissue+is%3Aopen+sort%3Aupdated-desc
Project-URL: Repository, https://github.com/litestar-org/litestar
Project-URL: Reddit, https://www.reddit.com/r/litestarapi
Project-URL: Twitter, https://twitter.com/LitestarAPI
